descriptive/__init__.py
descriptive/pydataprocessing.py
descriptive/pyeda.py
diagnostic/__init__.py
diagnostic/pydiagnostic.py
predictive/__init__.py
predictive/pypredictive.py
prescriptive/__init__.py
prescriptive/pyprescriptive.py
pydataanalysis-0.0.4.dist-info/LICENSE
pydataanalysis-0.0.4.dist-info/METADATA
pydataanalysis-0.0.4.dist-info/WHEEL
pydataanalysis-0.0.4.dist-info/top_level.txt
pydataanalysis-0.0.4.dist-info/RECORD
