Metadata-Version: 2.1
Name: pydataanalysis
Version: 0.0.4
Summary: Data Analysis and  Visualization Functions
Home-page: UNKNOWN
Author: Tamer Samara
Author-email: tamer.samara@gmail.com
License: MIT
Keywords: python,data science,eda,data preprocessing,data analysis,machine learning
Platform: UNKNOWN
Classifier: Programming Language :: Python :: 3
Classifier: Operating System :: Unix
Classifier: Operating System :: MacOS :: MacOS X
Classifier: Operating System :: Microsoft :: Windows
Requires-Dist: Pandas
Requires-Dist: Statsmodels
Requires-Dist: Seaborn
Requires-Dist: Matplotlib
Requires-Dist: SciPy
Requires-Dist: NumPy
Requires-Dist: Scikit-learn
